manimgeo/__init__.py
manimgeo/anime/__init__.py
manimgeo/anime/manager.py
manimgeo/anime/state.py
manimgeo/anime/janim/__init__.py
manimgeo/anime/janim/error_func.py
manimgeo/anime/janim/janim_manager.py
manimgeo/anime/manimgl/__init__.py
manimgeo/anime/manimgl/error_func.py
manimgeo/anime/manimgl/manimgl_manager.py
manimgeo/components/__init__.py
manimgeo/components/seq.py
manimgeo/components/angle/__init__.py
manimgeo/components/angle/adapter.py
manimgeo/components/angle/angle.py
manimgeo/components/angle/args.py
manimgeo/components/base/__init__.py
manimgeo/components/base/base_adapter.py
manimgeo/components/base/base_argsmodel.py
manimgeo/components/base/base_geometry.py
manimgeo/components/base/base_pydantic.py
manimgeo/components/circle/__init__.py
manimgeo/components/circle/adapter.py
manimgeo/components/circle/args.py
manimgeo/components/circle/circle.py
manimgeo/components/line/__init__.py
manimgeo/components/line/adapter.py
manimgeo/components/line/args.py
manimgeo/components/line/line.py
manimgeo/components/multiple/__init__.py
manimgeo/components/multiple/adapter.py
manimgeo/components/multiple/args.py
manimgeo/components/multiple/multiple.py
manimgeo/components/point/__init__.py
manimgeo/components/point/adapter.py
manimgeo/components/point/args.py
manimgeo/components/point/intersections.py
manimgeo/components/point/point.py
manimgeo/components/vector/__init__.py
manimgeo/components/vector/adapter.py
manimgeo/components/vector/args.py
manimgeo/components/vector/vector.py
manimgeo/math/__init__.py
manimgeo/math/angles.py
manimgeo/math/base.py
manimgeo/math/circles.py
manimgeo/math/intersections.py
manimgeo/math/lines.py
manimgeo/math/planes.py
manimgeo/math/points.py
manimgeo/math/three_points.py
manimgeo/math/vectors.py
manimgeo/utils/__init__.py
manimgeo/utils/config.py
manimgeo/utils/mathe.py
manimgeo/utils/output.py
manimgeo/utils/utils.py
manimgeo/utils/version.py
manimgeo-1.3.1a2.dist-info/licenses/LICENSE
manimgeo-1.3.1a2.dist-info/METADATA
manimgeo-1.3.1a2.dist-info/WHEEL
manimgeo-1.3.1a2.dist-info/top_level.txt
manimgeo-1.3.1a2.dist-info/RECORD
