Metadata-Version: 2.4
Name: manimgeo
Version: 1.3.1a2
Summary: A library for Geometry constructing and animation generating.
Author-email: lifecheckpoint <lifechpt@qq.com>
License-Expression: MIT
Project-URL: Homepage, https://github.com/LifeCheckpoint/ManimGeo
Requires-Python: >=3.12
License-File: LICENSE
Requires-Dist: numpy>=1.21.0
Requires-Dist: pydantic>=2.11.7
Provides-Extra: manim
Requires-Dist: manimgl>=1.7.2; extra == "manim"
Provides-Extra: janim
Requires-Dist: janim>=3.4.0; extra == "janim"
Requires-Dist: janim[gui]>=3.4.0; extra == "janim"
Provides-Extra: dev
Requires-Dist: furo>=2024.8.6; extra == "dev"
Requires-Dist: myst-parser>=4.0.1; extra == "dev"
Requires-Dist: py-spy>=0.4.0; extra == "dev"
Requires-Dist: pytest>=8.4.1; extra == "dev"
Requires-Dist: pytest-cov>=6.2.1; extra == "dev"
Requires-Dist: sphinx>=8.2.3; extra == "dev"
Requires-Dist: sphinx-autodoc-typehints>=3.2.0; extra == "dev"
Provides-Extra: full
Requires-Dist: manimgeo[manim]; extra == "full"
Requires-Dist: manimgeo[janim]; extra == "full"
Requires-Dist: manimgeo[dev]; extra == "full"
Dynamic: license-file
